LICENSE
README.md
setup.py
py2n/__init__.py
py2n/const.py
py2n/exceptions.py
py2n/model.py
py2n/utils.py
py2n.egg-info/PKG-INFO
py2n.egg-info/SOURCES.txt
py2n.egg-info/dependency_links.txt
py2n.egg-info/requires.txt
py2n.egg-info/top_level.txt
py2n.egg-info/zip-safe