Metadata-Version: 2.1
Name: py2n
Version: 0.4.1
Summary: Python library for 2N® devices
Home-page: https://github.com/elektr0nisch/py2n
Author: Linus Groschke
Author-email: linus@elektronisch.dev
License: MIT
Platform: any
Classifier: Intended Audience :: Developers
Classifier: Operating System :: OS Independent
Classifier: Programming Language :: Python
Classifier: Programming Language :: Python :: 3
Classifier: Programming Language :: Python :: 3.9
Classifier: Programming Language :: Python :: 3.10
Classifier: Topic :: Software Development :: Libraries :: Python Modules
Requires-Python: >=3.9
License-File: LICENSE
